{
  "stack": {
    "apis_cloud": [],
    "health_tech": [
      "HIPAA"
    ],
    "integration_patterns": [],
    "evidence": [
      {
        "claim": "1st Americare employs HIPAA compliance practices for data security and patient information protection.",
        "url": "https://www.1st-americare.com/security"
      }
    ],
    "tech_stack_confidence": 0.39
  },
  "icp": {
    "is_icp": false,
    "icp_reason": "No evidence of X12 or clearinghouse activity on their site.",
    "icp_confidence": 0.2,
    "matched_use_cases": []
  }
}