{
  "stack": {
    "apis_cloud": [],
    "health_tech": [],
    "integration_patterns": [],
    "evidence": [
      {
        "claim": "The company mentions their compliance with HIPAA regulations.",
        "url": "https://digitalworkforcesolution.com/security"
      },
      {
        "claim": "Digital Workforce Solution uses cloud technologies but specific services are not detailed on their site.",
        "url": "https://digitalworkforcesolution.com/services"
      },
      {
        "claim": "There is no direct mention of FHIR or HL7 integration capabilities on their webpages.",
        "url": "https://digitalworkforcesolution.com/health-tech"
      },
      {
        "claim": "The company focuses on data workflows but lacks specific cloud infrastructure details.",
        "url": "https://digitalworkforcesolution.com/about"
      }
    ],
    "tech_stack_confidence": 0.41
  },
  "icp": {
    "is_icp": false,
    "icp_reason": "No specific evidence found related to X12 or clearinghouse use cases.",
    "icp_confidence": 0.2,
    "matched_use_cases": []
  }
}